{
  "league_name": "Women's NC 3 North (South)",
  "league_url": "https://www.englandrugby.com/fixtures-and-results/search-results?competition=1782&division=56687&season=2024-2025#tables",
  "teams": [
    {
      "name": "Sale FC 1861 Women II",
      "url": "https://www.englandrugby.com/fixtures-and-results/search-results?team=123049&season=2024-2025",
      "image_url": "https://images.englandrugby.com/club_images/123049.png",
      "address": "Corpacq Stadium, Heywood Road, Brooklands, Sale, Cheshire, M33 3WB, United Kingdom",
      "latitude": 53.4173187,
      "longitude": -2.3215055,
      "formatted_address": "M33 3WB, Trafford, Greater Manchester, England, United Kingdom",
      "place_id": 350698118
    },
    {
      "name": "Macclesfield Women",
      "url": "https://www.englandrugby.com/fixtures-and-results/search-results?team=13069&season=2024-2025",
      "image_url": "https://images.englandrugby.com/club_images/13069.png",
      "address": "Priory Park, Priory Lane, Prestbury, Macclesfield, Cheshire, SK10 4AF, United Kingdom",
      "latitude": 53.2725255,
      "longitude": -2.1600659,
      "formatted_address": "Priory Park, Priory Lane, Manor Park, Prestbury, Macclesfield, Cheshire East, England, SK10 4AE, United Kingdom",
      "place_id": 255105008
    },
    {
      "name": "Liverpool Collegiate Ladies",
      "url": "https://www.englandrugby.com/fixtures-and-results/search-results?team=12418&season=2024-2025",
      "image_url": "https://images.englandrugby.com/club_images/12418.png",
      "address": "Liverpool Collegiate R.u.f.c. C/o Liverpool Cricket Club Aigburth Road Grassendale Liverpool Merseyside L19 3QF United Kingdom",
      "latitude": 53.36363,
      "longitude": -2.918,
      "formatted_address": "L19 3QF, Liverpool City Region, England, United Kingdom",
      "place_id": 350993734
    },
    {
      "name": "Stockport Scarlets Women",
      "url": "https://www.englandrugby.com/fixtures-and-results/search-results?team=26655&season=2024-2025",
      "image_url": "https://images.englandrugby.com/club_images/26655.png",
      "address": "Bridge Lane Memorial Ground Headlands Road Bramhall Stockport CHESHIRE SK7 3AN UNITED KINGDOM",
      "latitude": 53.37211,
      "longitude": -2.15291,
      "formatted_address": "SK7 3AN, Stockport, Greater Manchester, England, United Kingdom",
      "place_id": 351473010
    },
    {
      "name": "Moore Women",
      "url": "https://www.englandrugby.com/fixtures-and-results/search-results?team=94322&season=2024-2025",
      "image_url": "https://images.englandrugby.com/club_images/94322.png",
      "address": "Moss Lane Moore Warrington Cheshire WA4 6UU United Kingdom",
      "latitude": 53.3577779,
      "longitude": -2.637244,
      "formatted_address": "WA4 6UU, Moore, Halton, Liverpool City Region, England, United Kingdom",
      "place_id": 350430517
    },
    {
      "name": "Wirral Ladies",
      "url": "https://www.englandrugby.com/fixtures-and-results/search-results?team=94490&season=2024-2025",
      "image_url": "https://images.englandrugby.com/club_images/94490.png",
      "address": "Memorial Ground Thornton Common Road Clatterbridge Bebington MERSEYSIDE CH63 0LT UNITED KINGDOM",
      "latitude": 53.3243906,
      "longitude": -3.0198623,
      "formatted_address": "CH63 0LT, Wirral, Liverpool City Region, England, United Kingdom",
      "place_id": 350614529
    },
    {
      "name": "Glossop Women",
      "url": "https://www.englandrugby.com/fixtures-and-results/search-results?team=8618&season=2024-2025",
      "image_url": "https://images.englandrugby.com/club_images/8618.png",
      "address": "Hargate Hill Lane Charlesworth Glossop Derbyshire SK13 5HG United Kingdom",
      "latitude": 53.4379058,
      "longitude": -1.9874281,
      "formatted_address": "Hargate Hill Lane, Charlesworth, Gamesley, High Peak, Derbyshire, East Midlands, England, SK13 5HG, United Kingdom",
      "place_id": 253342903
    },
    {
      "name": "Ormskirk Ladies",
      "url": "https://www.englandrugby.com/fixtures-and-results/search-results?team=16254&season=2024-2025",
      "image_url": "https://images.englandrugby.com/club_images/16254.png",
      "address": "Green Lane Ormskirk LANCASHIRE L39 1ND UNITED KINGDOM",
      "latitude": 53.5723631,
      "longitude": -2.8872143,
      "formatted_address": "Green Lane, Ormskirk, West Lancashire, Lancashire, England, L39 1ND, United Kingdom",
      "place_id": 255393858
    },
    {
      "name": "Oldershaw Women",
      "url": "https://www.englandrugby.com/fixtures-and-results/search-results?team=127752&season=2024-2025",
      "image_url": "https://images.englandrugby.com/club_images/127752.png",
      "address": "Bevidere Recreation Ground Belvidere Field Belvidere Road, Wallasey Wallasey MERSEYSIDE CH45 4RZ ENGLAND",
      "latitude": 53.42299,
      "longitude": -3.05297,
      "formatted_address": "CH45 4RZ, Wirral, Liverpool City Region, England, United Kingdom",
      "place_id": 350610804
    }
  ],
  "team_count": 9
}