{
  "league_name": "Midlands 2 East (South)",
  "league_url": "https://www.englandrugby.com/fixtures-and-results/search-results?competition=1597&division=21483&season=2019-2020#tables",
  "teams": [
    {
      "name": "Leighton Buzzard",
      "url": "https://www.englandrugby.com/fixtures-and-results/search-results?team=12141",
      "image_url": "https://images.englandrugby.com/club_images/12141.png",
      "address": "Leighton Buzzard Rfc, Wright's Meadow, Leighton Road, Stanbridge, Leighton Buzzard, Bedfordshire, LU7 9HR, United Kingdom",
      "latitude": 51.9090925,
      "longitude": -0.6169415,
      "formatted_address": "LU7 9HR, Stanbridge, Central Bedfordshire, England, United Kingdom",
      "place_id": 350694207
    },
    {
      "name": "Belgrave",
      "url": "https://www.englandrugby.com/fixtures-and-results/search-results?team=1895",
      "image_url": "https://images.englandrugby.com/club_images/1895.png",
      "address": "Belgrave Pastures Thurcaston Road Abbey Lane LEICESTERSHIRE LE4 2QG UNITED KINGDOM ",
      "latitude": 52.66481,
      "longitude": -1.13313,
      "formatted_address": "LE4 2QG, Redhill Nook Travellers Site, Mowmacre Hill, Leicester, City of Leicester, England, United Kingdom",
      "place_id": 351480553
    },
    {
      "name": "Leicester Forest",
      "url": "https://www.englandrugby.com/fixtures-and-results/search-results?team=12046",
      "image_url": "https://images.englandrugby.com/club_images/12046.png",
      "address": "Leicester Forest R.f.c. Hinckley Road Leicester Forest East Leicester Leicestershire LE3 3PJ United Kingdom",
      "latitude": 52.6188547,
      "longitude": -1.2355742,
      "formatted_address": "LE3 3PJ, Kirby Muxloe, Blaby, Leicestershire, England, United Kingdom",
      "place_id": 350683795
    },
    {
      "name": "Market Bosworth",
      "url": "https://www.englandrugby.com/fixtures-and-results/search-results?team=13349",
      "image_url": "https://images.englandrugby.com/club_images/13349.png",
      "address": "Market Bosworth R.f.c. Cadeby Lane Cadeby Market Bosworth Nuneaton Warwickshire CV13 0BA United Kingdom",
      "latitude": 52.62421,
      "longitude": -1.38332,
      "formatted_address": "CV13 0BA, Cadeby, Market Bosworth, Hinckley and Bosworth, Leicestershire, England, United Kingdom",
      "place_id": 351113537
    },
    {
      "name": "Bugbrooke",
      "url": "https://www.englandrugby.com/fixtures-and-results/search-results?team=3627",
      "image_url": "https://images.englandrugby.com/club_images/3627.png",
      "address": "Bugbrooke Rugby Union Football Club Camp Close Bugbrooke Northamptonshire NN7 3RW United Kingdom",
      "latitude": 52.2071724,
      "longitude": -1.0042639,
      "formatted_address": "NN7 3RW, Bugbrooke, West Northamptonshire, England, United Kingdom",
      "place_id": 350728227
    },
    {
      "name": "Northampton Old Scouts",
      "url": "https://www.englandrugby.com/fixtures-and-results/search-results?team=14907",
      "image_url": "https://images.englandrugby.com/club_images/14907.png",
      "address": "Rushmere Road Northampton NORTHAMPTONSHIRE NN1 5RY UNITED KINGDOM ",
      "latitude": 52.2357568,
      "longitude": -0.8616714,
      "formatted_address": "Rushmere Road, Abington, Northampton, West Northamptonshire, England, NN1 5RY, United Kingdom",
      "place_id": 258808095
    },
    {
      "name": "Vipers",
      "url": "https://www.englandrugby.com/fixtures-and-results/search-results?team=24033",
      "image_url": "https://images.englandrugby.com/club_images/24033.png",
      "address": "Blaby Bypass, Whetstone, Leicester, LE8 6DA, United Kingdom",
      "latitude": 52.573137,
      "longitude": -1.1725976,
      "formatted_address": "LE8 6DA, Blaby, Leicestershire, England, United Kingdom",
      "place_id": 351486673
    },
    {
      "name": "Northampton Casuals",
      "url": "https://www.englandrugby.com/fixtures-and-results/search-results?team=14872",
      "image_url": "https://images.englandrugby.com/club_images/14872.png",
      "address": "Rush Mills House, Old Bedford Road, Rush Mills, Northampton, Northamptonshire, NN4 7AA, United Kingdom",
      "latitude": 52.2278993,
      "longitude": -0.8637056,
      "formatted_address": "NN4 7AA, Brackmills Industrial Estate, Brackmills, Hardingstone, West Northamptonshire, England, United Kingdom",
      "place_id": 350727046
    },
    {
      "name": "St Ives (Midlands)",
      "url": "https://www.englandrugby.com/fixtures-and-results/search-results?team=20424",
      "image_url": "https://images.englandrugby.com/club_images/20424.png",
      "address": "St Ives (Midlands) Somersham Road St. Ives CAMBRIDGESHIRE PE27 3LY UNITED KINGDOM ",
      "latitude": 52.3474607,
      "longitude": -0.0603848,
      "formatted_address": "PE27 3LY, St. Ives, Huntingdonshire, Cambridgeshire, Cambridgeshire and Peterborough, England, United Kingdom",
      "place_id": 350762164
    },
    {
      "name": "Long Buckby",
      "url": "https://www.englandrugby.com/fixtures-and-results/search-results?team=12676",
      "image_url": "https://images.englandrugby.com/club_images/12676.png",
      "address": "Long Buckby Rugby Football Club Station Road Long Buckby Northampton Northamptonshire NN6 7QA United Kingdom",
      "latitude": 52.298379,
      "longitude": -1.0842189,
      "formatted_address": "NN6 7QA, Long Buckby, West Northamptonshire, England, United Kingdom",
      "place_id": 350727792
    },
    {
      "name": "Melton Mowbray",
      "url": "https://www.englandrugby.com/fixtures-and-results/search-results?team=13693",
      "image_url": "https://images.englandrugby.com/club_images/13693.png",
      "address": "Burton Rd Melton Mowbray LE13 1DR ENGLAND",
      "latitude": 52.7528715,
      "longitude": -0.8773902,
      "formatted_address": "Burton Road, Melton Mowbray, Melton, Leicestershire, England, LE13 1DR, United Kingdom",
      "place_id": 406543907
    },
    {
      "name": "Stewarts & Lloyds",
      "url": "https://www.englandrugby.com/fixtures-and-results/search-results?team=20949",
      "image_url": "https://images.englandrugby.com/club_images/20949.png",
      "address": "Stewarts & Lloyds R.f.c. The Clubhouse Occupation Road Corby Northamptonshire NN17 1EH United Kingdom",
      "latitude": 52.4988589,
      "longitude": -0.6914631,
      "formatted_address": "NN17 1EH, North Northamptonshire, England, United Kingdom",
      "place_id": 350726271
    }
  ],
  "team_count": 12
}
