{
  "league_name": "Midlands 3 West (South)",
  "league_url": "https://www.englandrugby.com/fixtures-and-results/search-results?competition=1597&division=2687&season=2005-2006#tables",
  "fixtures": [
    {
      "date": "2005-09-03",
      "time": "",
      "home_team_id": 7088,
      "away_team_id": 1865,
      "match_url": "https://www.englandrugby.com/fixtures-and-results/match-centre-community?matchId=90018",
      "home_score": 17,
      "away_score": 12
    },
    {
      "date": "2005-09-03",
      "time": "",
      "home_team_id": 11294,
      "away_team_id": 19548,
      "match_url": "https://www.englandrugby.com/fixtures-and-results/match-centre-community?matchId=90020",
      "home_score": 15,
      "away_score": 22
    },
    {
      "date": "2005-09-03",
      "time": "",
      "home_team_id": 15578,
      "away_team_id": 11963,
      "match_url": "https://www.englandrugby.com/fixtures-and-results/match-centre-community?matchId=90058",
      "home_score": 42,
      "away_score": 17
    },
    {
      "date": "2005-09-03",
      "time": "",
      "home_team_id": 16795,
      "away_team_id": 15805,
      "match_url": "https://www.englandrugby.com/fixtures-and-results/match-centre-community?matchId=90059",
      "home_score": 35,
      "away_score": 17
    },
    {
      "date": "2005-09-03",
      "time": "",
      "home_team_id": 19363,
      "away_team_id": 15197,
      "match_url": "https://www.englandrugby.com/fixtures-and-results/match-centre-community?matchId=90021",
      "home_score": 48,
      "away_score": 23
    },
    {
      "date": "2005-09-03",
      "time": "",
      "home_team_id": 21232,
      "away_team_id": 10011,
      "match_url": "https://www.englandrugby.com/fixtures-and-results/match-centre-community?matchId=90019",
      "home_score": 24,
      "away_score": 20
    },
    {
      "date": "2005-09-10",
      "time": "",
      "home_team_id": 1865,
      "away_team_id": 10011,
      "match_url": "https://www.englandrugby.com/fixtures-and-results/match-centre-community?matchId=92425",
      "home_score": 27,
      "away_score": 14
    },
    {
      "date": "2005-09-10",
      "time": "",
      "home_team_id": 7088,
      "away_team_id": 11294,
      "match_url": "https://www.englandrugby.com/fixtures-and-results/match-centre-community?matchId=92426",
      "home_score": 17,
      "away_score": 3
    },
    {
      "date": "2005-09-10",
      "time": "",
      "home_team_id": 11963,
      "away_team_id": 16795,
      "match_url": "https://www.englandrugby.com/fixtures-and-results/match-centre-community?matchId=92430",
      "home_score": 0,
      "away_score": 39
    },
    {
      "date": "2005-09-10",
      "time": "",
      "home_team_id": 15197,
      "away_team_id": 21232,
      "match_url": "https://www.englandrugby.com/fixtures-and-results/match-centre-community?matchId=92427",
      "home_score": 8,
      "away_score": 14
    },
    {
      "date": "2005-09-10",
      "time": "",
      "home_team_id": 15805,
      "away_team_id": 19363,
      "match_url": "https://www.englandrugby.com/fixtures-and-results/match-centre-community?matchId=92429",
      "home_score": 13,
      "away_score": 39
    },
    {
      "date": "2005-09-10",
      "time": "",
      "home_team_id": 19548,
      "away_team_id": 15578,
      "match_url": "https://www.englandrugby.com/fixtures-and-results/match-centre-community?matchId=92428",
      "home_score": 10,
      "away_score": 0
    },
    {
      "date": "2005-09-24",
      "time": "",
      "home_team_id": 10011,
      "away_team_id": 15197,
      "match_url": "https://www.englandrugby.com/fixtures-and-results/match-centre-community?matchId=92432",
      "home_score": 21,
      "away_score": 14
    },
    {
      "date": "2005-09-24",
      "time": "",
      "home_team_id": 11294,
      "away_team_id": 1865,
      "match_url": "https://www.englandrugby.com/fixtures-and-results/match-centre-community?matchId=92431",
      "home_score": 5,
      "away_score": 18
    },
    {
      "date": "2005-09-24",
      "time": "",
      "home_team_id": 15578,
      "away_team_id": 7088,
      "match_url": "https://www.englandrugby.com/fixtures-and-results/match-centre-community?matchId=92433",
      "home_score": 13,
      "away_score": 27
    },
    {
      "date": "2005-09-24",
      "time": "",
      "home_team_id": 16795,
      "away_team_id": 19548,
      "match_url": "https://www.englandrugby.com/fixtures-and-results/match-centre-community?matchId=92435",
      "home_score": 8,
      "away_score": 19
    },
    {
      "date": "2005-09-24",
      "time": "",
      "home_team_id": 19363,
      "away_team_id": 11963,
      "match_url": "https://www.englandrugby.com/fixtures-and-results/match-centre-community?matchId=92436",
      "home_score": 38,
      "away_score": 0
    },
    {
      "date": "2005-09-24",
      "time": "",
      "home_team_id": 21232,
      "away_team_id": 15805,
      "match_url": "https://www.englandrugby.com/fixtures-and-results/match-centre-community?matchId=92434",
      "home_score": 48,
      "away_score": 10
    },
    {
      "date": "2005-10-01",
      "time": "",
      "home_team_id": 7088,
      "away_team_id": 16795,
      "match_url": "https://www.englandrugby.com/fixtures-and-results/match-centre-community?matchId=92440",
      "home_score": 27,
      "away_score": 21
    },
    {
      "date": "2005-10-01",
      "time": "",
      "home_team_id": 11294,
      "away_team_id": 15578,
      "match_url": "https://www.englandrugby.com/fixtures-and-results/match-centre-community?matchId=92438",
      "home_score": 3,
      "away_score": 20
    },
    {
      "date": "2005-10-01",
      "time": "",
      "home_team_id": 11963,
      "away_team_id": 21232,
      "match_url": "https://www.englandrugby.com/fixtures-and-results/match-centre-community?matchId=92441",
      "home_score": 14,
      "away_score": 48
    },
    {
      "date": "2005-10-01",
      "time": "",
      "home_team_id": 15805,
      "away_team_id": 10011,
      "match_url": "https://www.englandrugby.com/fixtures-and-results/match-centre-community?matchId=92439",
      "home_score": 10,
      "away_score": 22
    },
    {
      "date": "2005-10-01",
      "time": "",
      "home_team_id": 19548,
      "away_team_id": 19363,
      "match_url": "https://www.englandrugby.com/fixtures-and-results/match-centre-community?matchId=92442",
      "home_score": 14,
      "away_score": 22
    },
    {
      "date": "2005-10-08",
      "time": "",
      "home_team_id": 10011,
      "away_team_id": 11963,
      "match_url": "https://www.englandrugby.com/fixtures-and-results/match-centre-community?matchId=92446",
      "home_score": 47,
      "away_score": 0
    },
    {
      "date": "2005-10-08",
      "time": "",
      "home_team_id": 15197,
      "away_team_id": 15805,
      "match_url": "https://www.englandrugby.com/fixtures-and-results/match-centre-community?matchId=92444",
      "home_score": 55,
      "away_score": 0
    },
    {
      "date": "2005-10-08",
      "time": "",
      "home_team_id": 15578,
      "away_team_id": 1865,
      "match_url": "https://www.englandrugby.com/fixtures-and-results/match-centre-community?matchId=92443",
      "home_score": 14,
      "away_score": 3
    },
    {
      "date": "2005-10-08",
      "time": "",
      "home_team_id": 16795,
      "away_team_id": 11294,
      "match_url": "https://www.englandrugby.com/fixtures-and-results/match-centre-community?matchId=92445",
      "home_score": 50,
      "away_score": 3
    },
    {
      "date": "2005-10-08",
      "time": "",
      "home_team_id": 19363,
      "away_team_id": 7088,
      "match_url": "https://www.englandrugby.com/fixtures-and-results/match-centre-community?matchId=92447",
      "home_score": 17,
      "away_score": 8
    },
    {
      "date": "2005-10-08",
      "time": "",
      "home_team_id": 21232,
      "away_team_id": 19548,
      "match_url": "https://www.englandrugby.com/fixtures-and-results/match-centre-community?matchId=92448",
      "home_score": 8,
      "away_score": 39
    },
    {
      "date": "2005-10-15",
      "time": "",
      "home_team_id": 1865,
      "away_team_id": 15197,
      "match_url": "https://www.englandrugby.com/fixtures-and-results/match-centre-community?matchId=92437",
      "home_score": 18,
      "away_score": 7
    },
    {
      "date": "2005-10-22",
      "time": "",
      "home_team_id": 1865,
      "away_team_id": 15805,
      "match_url": "https://www.englandrugby.com/fixtures-and-results/match-centre-community?matchId=92449",
      "home_score": 28,
      "away_score": 18
    },
    {
      "date": "2005-10-22",
      "time": "",
      "home_team_id": 7088,
      "away_team_id": 21232,
      "match_url": "https://www.englandrugby.com/fixtures-and-results/match-centre-community?matchId=92454",
      "home_score": 11,
      "away_score": 23
    },
    {
      "date": "2005-10-22",
      "time": "",
      "home_team_id": 11294,
      "away_team_id": 19363,
      "match_url": "https://www.englandrugby.com/fixtures-and-results/match-centre-community?matchId=92452",
      "home_score": 7,
      "away_score": 27
    },
    {
      "date": "2005-10-22",
      "time": "",
      "home_team_id": 11963,
      "away_team_id": 15197,
      "match_url": "https://www.englandrugby.com/fixtures-and-results/match-centre-community?matchId=92451",
      "home_score": 5,
      "away_score": 39
    },
    {
      "date": "2005-10-22",
      "time": "",
      "home_team_id": 15578,
      "away_team_id": 16795,
      "match_url": "https://www.englandrugby.com/fixtures-and-results/match-centre-community?matchId=92450",
      "home_score": 10,
      "away_score": 34
    },
    {
      "date": "2005-10-22",
      "time": "",
      "home_team_id": 19548,
      "away_team_id": 10011,
      "match_url": "https://www.englandrugby.com/fixtures-and-results/match-centre-community?matchId=92453",
      "home_score": 24,
      "away_score": 17
    },
    {
      "date": "2005-10-29",
      "time": "",
      "home_team_id": 10011,
      "away_team_id": 7088,
      "match_url": "https://www.englandrugby.com/fixtures-and-results/match-centre-community?matchId=92459",
      "home_score": 29,
      "away_score": 20
    },
    {
      "date": "2005-10-29",
      "time": "",
      "home_team_id": 16795,
      "away_team_id": 1865,
      "match_url": "https://www.englandrugby.com/fixtures-and-results/match-centre-community?matchId=92455",
      "home_score": 8,
      "away_score": 14
    },
    {
      "date": "2005-10-29",
      "time": "",
      "home_team_id": 19363,
      "away_team_id": 15578,
      "match_url": "https://www.englandrugby.com/fixtures-and-results/match-centre-community?matchId=92457",
      "home_score": 50,
      "away_score": 14
    },
    {
      "date": "2005-10-29",
      "time": "",
      "home_team_id": 19548,
      "away_team_id": 15197,
      "match_url": "https://www.englandrugby.com/fixtures-and-results/match-centre-community?matchId=92749",
      "home_score": 24,
      "away_score": 10
    },
    {
      "date": "2005-10-29",
      "time": "",
      "home_team_id": 21232,
      "away_team_id": 11294,
      "match_url": "https://www.englandrugby.com/fixtures-and-results/match-centre-community?matchId=92458",
      "home_score": 31,
      "away_score": 0
    },
    {
      "date": "2005-11-12",
      "time": "",
      "home_team_id": 1865,
      "away_team_id": 11963,
      "match_url": "https://www.englandrugby.com/fixtures-and-results/match-centre-community?matchId=92460",
      "home_score": 55,
      "away_score": 3
    },
    {
      "date": "2005-11-12",
      "time": "",
      "home_team_id": 7088,
      "away_team_id": 15197,
      "match_url": "https://www.englandrugby.com/fixtures-and-results/match-centre-community?matchId=92463",
      "home_score": 16,
      "away_score": 18
    },
    {
      "date": "2005-11-12",
      "time": "",
      "home_team_id": 11294,
      "away_team_id": 10011,
      "match_url": "https://www.englandrugby.com/fixtures-and-results/match-centre-community?matchId=92464",
      "home_score": 7,
      "away_score": 48
    },
    {
      "date": "2005-11-12",
      "time": "",
      "home_team_id": 15578,
      "away_team_id": 21232,
      "match_url": "https://www.englandrugby.com/fixtures-and-results/match-centre-community?matchId=92462",
      "home_score": 12,
      "away_score": 25
    },
    {
      "date": "2005-11-12",
      "time": "",
      "home_team_id": 15805,
      "away_team_id": 19548,
      "match_url": "https://www.englandrugby.com/fixtures-and-results/match-centre-community?matchId=92750",
      "home_score": 5,
      "away_score": 34
    },
    {
      "date": "2005-11-12",
      "time": "",
      "home_team_id": 16795,
      "away_team_id": 19363,
      "match_url": "https://www.englandrugby.com/fixtures-and-results/match-centre-community?matchId=92461",
      "home_score": 15,
      "away_score": 31
    },
    {
      "date": "2005-11-19",
      "time": "",
      "home_team_id": 10011,
      "away_team_id": 15578,
      "match_url": "https://www.englandrugby.com/fixtures-and-results/match-centre-community?matchId=92469",
      "home_score": 33,
      "away_score": 3
    },
    {
      "date": "2005-11-19",
      "time": "",
      "home_team_id": 11963,
      "away_team_id": 19548,
      "match_url": "https://www.englandrugby.com/fixtures-and-results/match-centre-community?matchId=92466",
      "home_score": 10,
      "away_score": 46
    },
    {
      "date": "2005-11-19",
      "time": "",
      "home_team_id": 15197,
      "away_team_id": 11294,
      "match_url": "https://www.englandrugby.com/fixtures-and-results/match-centre-community?matchId=92470",
      "home_score": 29,
      "away_score": 13
    },
    {
      "date": "2005-11-19",
      "time": "",
      "home_team_id": 19363,
      "away_team_id": 1865,
      "match_url": "https://www.englandrugby.com/fixtures-and-results/match-centre-community?matchId=92465",
      "home_score": 31,
      "away_score": 10
    },
    {
      "date": "2005-11-26",
      "time": "",
      "home_team_id": 15805,
      "away_team_id": 11963,
      "match_url": "https://www.englandrugby.com/fixtures-and-results/match-centre-community?matchId=92456",
      "home_score": 17,
      "away_score": 20
    },
    {
      "date": "2005-11-26",
      "time": "",
      "home_team_id": 21232,
      "away_team_id": 16795,
      "match_url": "https://www.englandrugby.com/fixtures-and-results/match-centre-community?matchId=92467",
      "home_score": 20,
      "away_score": 17
    },
    {
      "date": "2005-12-03",
      "time": "",
      "home_team_id": 1865,
      "away_team_id": 19548,
      "match_url": "https://www.englandrugby.com/fixtures-and-results/match-centre-community?matchId=92471",
      "home_score": 7,
      "away_score": 48
    },
    {
      "date": "2005-12-03",
      "time": "",
      "home_team_id": 7088,
      "away_team_id": 11963,
      "match_url": "https://www.englandrugby.com/fixtures-and-results/match-centre-community?matchId=92473",
      "home_score": 20,
      "away_score": 17
    },
    {
      "date": "2005-12-03",
      "time": "",
      "home_team_id": 11294,
      "away_team_id": 15805,
      "match_url": "https://www.englandrugby.com/fixtures-and-results/match-centre-community?matchId=92475",
      "home_score": 5,
      "away_score": 6
    },
    {
      "date": "2005-12-03",
      "time": "",
      "home_team_id": 15578,
      "away_team_id": 15197,
      "match_url": "https://www.englandrugby.com/fixtures-and-results/match-centre-community?matchId=92476",
      "home_score": 15,
      "away_score": 21
    },
    {
      "date": "2005-12-10",
      "time": "",
      "home_team_id": 10011,
      "away_team_id": 19363,
      "match_url": "https://www.englandrugby.com/fixtures-and-results/match-centre-community?matchId=92479",
      "home_score": 26,
      "away_score": 15
    },
    {
      "date": "2005-12-10",
      "time": "",
      "home_team_id": 15197,
      "away_team_id": 16795,
      "match_url": "https://www.englandrugby.com/fixtures-and-results/match-centre-community?matchId=92481",
      "home_score": 21,
      "away_score": 20
    },
    {
      "date": "2005-12-10",
      "time": "",
      "home_team_id": 15805,
      "away_team_id": 15578,
      "match_url": "https://www.englandrugby.com/fixtures-and-results/match-centre-community?matchId=92482",
      "home_score": 28,
      "away_score": 20
    },
    {
      "date": "2005-12-10",
      "time": "",
      "home_team_id": 19548,
      "away_team_id": 7088,
      "match_url": "https://www.englandrugby.com/fixtures-and-results/match-centre-community?matchId=92478",
      "home_score": 35,
      "away_score": 6
    },
    {
      "date": "2005-12-10",
      "time": "",
      "home_team_id": 21232,
      "away_team_id": 1865,
      "match_url": "https://www.englandrugby.com/fixtures-and-results/match-centre-community?matchId=92477",
      "home_score": 13,
      "away_score": 17
    },
    {
      "date": "2005-12-17",
      "time": "",
      "home_team_id": 1865,
      "away_team_id": 19363,
      "match_url": "https://www.englandrugby.com/fixtures-and-results/match-centre-community?matchId=92483",
      "home_score": 24,
      "away_score": 21
    },
    {
      "date": "2005-12-17",
      "time": "",
      "home_team_id": 7088,
      "away_team_id": 15805,
      "match_url": "https://www.englandrugby.com/fixtures-and-results/match-centre-community?matchId=92486",
      "home_score": 22,
      "away_score": 23
    },
    {
      "date": "2005-12-17",
      "time": "",
      "home_team_id": 15578,
      "away_team_id": 10011,
      "match_url": "https://www.englandrugby.com/fixtures-and-results/match-centre-community?matchId=92487",
      "home_score": 10,
      "away_score": 29
    },
    {
      "date": "2006-01-07",
      "time": "",
      "home_team_id": 10011,
      "away_team_id": 11294,
      "match_url": "https://www.englandrugby.com/fixtures-and-results/match-centre-community?matchId=92493",
      "home_score": 67,
      "away_score": 0
    },
    {
      "date": "2006-01-07",
      "time": "",
      "home_team_id": 11963,
      "away_team_id": 1865,
      "match_url": "https://www.englandrugby.com/fixtures-and-results/match-centre-community?matchId=92489",
      "home_score": 15,
      "away_score": 13
    },
    {
      "date": "2006-01-07",
      "time": "",
      "home_team_id": 15197,
      "away_team_id": 7088,
      "match_url": "https://www.englandrugby.com/fixtures-and-results/match-centre-community?matchId=92492",
      "home_score": 7,
      "away_score": 8
    },
    {
      "date": "2006-01-07",
      "time": "",
      "home_team_id": 19363,
      "away_team_id": 16795,
      "match_url": "https://www.englandrugby.com/fixtures-and-results/match-centre-community?matchId=92490",
      "home_score": 15,
      "away_score": 9
    },
    {
      "date": "2006-01-07",
      "time": "",
      "home_team_id": 19548,
      "away_team_id": 15805,
      "match_url": "https://www.englandrugby.com/fixtures-and-results/match-centre-community?matchId=92751",
      "home_score": 41,
      "away_score": 0
    },
    {
      "date": "2006-01-07",
      "time": "",
      "home_team_id": 21232,
      "away_team_id": 15578,
      "match_url": "https://www.englandrugby.com/fixtures-and-results/match-centre-community?matchId=92491",
      "home_score": 29,
      "away_score": 8
    },
    {
      "date": "2006-01-14",
      "time": "",
      "home_team_id": 11963,
      "away_team_id": 11294,
      "match_url": "https://www.englandrugby.com/fixtures-and-results/match-centre-community?matchId=92480",
      "home_score": 32,
      "away_score": 15
    },
    {
      "date": "2006-01-14",
      "time": "",
      "home_team_id": 15805,
      "away_team_id": 7088,
      "match_url": "https://www.englandrugby.com/fixtures-and-results/match-centre-community?matchId=92468",
      "home_score": 27,
      "away_score": 28
    },
    {
      "date": "2006-01-14",
      "time": "",
      "home_team_id": 16795,
      "away_team_id": 10011,
      "match_url": "https://www.englandrugby.com/fixtures-and-results/match-centre-community?matchId=92474",
      "home_score": 0,
      "away_score": 80
    },
    {
      "date": "2006-01-21",
      "time": "",
      "home_team_id": 1865,
      "away_team_id": 16795,
      "match_url": "https://www.englandrugby.com/fixtures-and-results/match-centre-community?matchId=92494",
      "home_score": 20,
      "away_score": 12
    },
    {
      "date": "2006-01-21",
      "time": "",
      "home_team_id": 7088,
      "away_team_id": 10011,
      "match_url": "https://www.englandrugby.com/fixtures-and-results/match-centre-community?matchId=92498",
      "home_score": 7,
      "away_score": 24
    },
    {
      "date": "2006-01-21",
      "time": "",
      "home_team_id": 11294,
      "away_team_id": 21232,
      "match_url": "https://www.englandrugby.com/fixtures-and-results/match-centre-community?matchId=92497",
      "home_score": 14,
      "away_score": 36
    },
    {
      "date": "2006-01-21",
      "time": "",
      "home_team_id": 11963,
      "away_team_id": 15805,
      "match_url": "https://www.englandrugby.com/fixtures-and-results/match-centre-community?matchId=92495",
      "home_score": 29,
      "away_score": 10
    },
    {
      "date": "2006-01-21",
      "time": "",
      "home_team_id": 15197,
      "away_team_id": 19548,
      "match_url": "https://www.englandrugby.com/fixtures-and-results/match-centre-community?matchId=92752",
      "home_score": 5,
      "away_score": 32
    },
    {
      "date": "2006-01-21",
      "time": "",
      "home_team_id": 15578,
      "away_team_id": 19363,
      "match_url": "https://www.englandrugby.com/fixtures-and-results/match-centre-community?matchId=92496",
      "home_score": 12,
      "away_score": 29
    },
    {
      "date": "2006-01-28",
      "time": "",
      "home_team_id": 10011,
      "away_team_id": 19548,
      "match_url": "https://www.englandrugby.com/fixtures-and-results/match-centre-community?matchId=92503",
      "home_score": 11,
      "away_score": 25
    },
    {
      "date": "2006-01-28",
      "time": "",
      "home_team_id": 15197,
      "away_team_id": 11963,
      "match_url": "https://www.englandrugby.com/fixtures-and-results/match-centre-community?matchId=92501",
      "home_score": 46,
      "away_score": 8
    },
    {
      "date": "2006-01-28",
      "time": "",
      "home_team_id": 15805,
      "away_team_id": 1865,
      "match_url": "https://www.englandrugby.com/fixtures-and-results/match-centre-community?matchId=92499",
      "home_score": 16,
      "away_score": 20
    },
    {
      "date": "2006-01-28",
      "time": "",
      "home_team_id": 16795,
      "away_team_id": 15578,
      "match_url": "https://www.englandrugby.com/fixtures-and-results/match-centre-community?matchId=92500",
      "home_score": 18,
      "away_score": 19
    },
    {
      "date": "2006-01-28",
      "time": "",
      "home_team_id": 19363,
      "away_team_id": 11294,
      "match_url": "https://www.englandrugby.com/fixtures-and-results/match-centre-community?matchId=92502",
      "home_score": 57,
      "away_score": 7
    },
    {
      "date": "2006-01-28",
      "time": "",
      "home_team_id": 21232,
      "away_team_id": 7088,
      "match_url": "https://www.englandrugby.com/fixtures-and-results/match-centre-community?matchId=92504",
      "home_score": 45,
      "away_score": 10
    },
    {
      "date": "2006-02-04",
      "time": "",
      "home_team_id": 11294,
      "away_team_id": 15197,
      "match_url": "https://www.englandrugby.com/fixtures-and-results/match-centre-community?matchId=92488",
      "home_score": 0,
      "away_score": 33
    },
    {
      "date": "2006-02-04",
      "time": "",
      "home_team_id": 19548,
      "away_team_id": 11963,
      "match_url": "https://www.englandrugby.com/fixtures-and-results/match-centre-community?matchId=92484",
      "home_score": 74,
      "away_score": 7
    },
    {
      "date": "2006-02-11",
      "time": "",
      "home_team_id": 1865,
      "away_team_id": 15578,
      "match_url": "https://www.englandrugby.com/fixtures-and-results/match-centre-community?matchId=92505",
      "home_score": 27,
      "away_score": 10
    },
    {
      "date": "2006-02-11",
      "time": "",
      "home_team_id": 7088,
      "away_team_id": 19363,
      "match_url": "https://www.englandrugby.com/fixtures-and-results/match-centre-community?matchId=92509",
      "home_score": 12,
      "away_score": 17
    },
    {
      "date": "2006-02-11",
      "time": "",
      "home_team_id": 11294,
      "away_team_id": 16795,
      "match_url": "https://www.englandrugby.com/fixtures-and-results/match-centre-community?matchId=92507",
      "home_score": 3,
      "away_score": 29
    },
    {
      "date": "2006-02-11",
      "time": "",
      "home_team_id": 11963,
      "away_team_id": 10011,
      "match_url": "https://www.englandrugby.com/fixtures-and-results/match-centre-community?matchId=92508",
      "home_score": 7,
      "away_score": 42
    },
    {
      "date": "2006-02-11",
      "time": "",
      "home_team_id": 15805,
      "away_team_id": 15197,
      "match_url": "https://www.englandrugby.com/fixtures-and-results/match-centre-community?matchId=92506",
      "home_score": 22,
      "away_score": 39
    },
    {
      "date": "2006-02-11",
      "time": "",
      "home_team_id": 19548,
      "away_team_id": 21232,
      "match_url": "https://www.englandrugby.com/fixtures-and-results/match-centre-community?matchId=92510",
      "home_score": 14,
      "away_score": 3
    },
    {
      "date": "2006-02-18",
      "time": "",
      "home_team_id": 10011,
      "away_team_id": 15805,
      "match_url": "https://www.englandrugby.com/fixtures-and-results/match-centre-community?matchId=92513",
      "home_score": 64,
      "away_score": 17
    },
    {
      "date": "2006-02-18",
      "time": "",
      "home_team_id": 15197,
      "away_team_id": 1865,
      "match_url": "https://www.englandrugby.com/fixtures-and-results/match-centre-community?matchId=92511",
      "home_score": 20,
      "away_score": 7
    },
    {
      "date": "2006-02-18",
      "time": "",
      "home_team_id": 15578,
      "away_team_id": 11294,
      "match_url": "https://www.englandrugby.com/fixtures-and-results/match-centre-community?matchId=92512",
      "home_score": 29,
      "away_score": 25
    },
    {
      "date": "2006-02-18",
      "time": "",
      "home_team_id": 16795,
      "away_team_id": 7088,
      "match_url": "https://www.englandrugby.com/fixtures-and-results/match-centre-community?matchId=92515",
      "home_score": 27,
      "away_score": 5
    },
    {
      "date": "2006-02-18",
      "time": "",
      "home_team_id": 19363,
      "away_team_id": 19548,
      "match_url": "https://www.englandrugby.com/fixtures-and-results/match-centre-community?matchId=92516",
      "home_score": 11,
      "away_score": 20
    },
    {
      "date": "2006-02-18",
      "time": "",
      "home_team_id": 21232,
      "away_team_id": 11963,
      "match_url": "https://www.englandrugby.com/fixtures-and-results/match-centre-community?matchId=92514",
      "home_score": 36,
      "away_score": 14
    },
    {
      "date": "2006-03-04",
      "time": "",
      "home_team_id": 1865,
      "away_team_id": 11294,
      "match_url": "https://www.englandrugby.com/fixtures-and-results/match-centre-community?matchId=92517",
      "home_score": 18,
      "away_score": 11
    },
    {
      "date": "2006-03-04",
      "time": "",
      "home_team_id": 7088,
      "away_team_id": 15578,
      "match_url": "https://www.englandrugby.com/fixtures-and-results/match-centre-community?matchId=92519",
      "home_score": 13,
      "away_score": 12
    },
    {
      "date": "2006-03-04",
      "time": "",
      "home_team_id": 11963,
      "away_team_id": 19363,
      "match_url": "https://www.englandrugby.com/fixtures-and-results/match-centre-community?matchId=92522",
      "home_score": 27,
      "away_score": 9
    },
    {
      "date": "2006-03-04",
      "time": "",
      "home_team_id": 15197,
      "away_team_id": 10011,
      "match_url": "https://www.englandrugby.com/fixtures-and-results/match-centre-community?matchId=92518",
      "home_score": 11,
      "away_score": 22
    },
    {
      "date": "2006-03-04",
      "time": "",
      "home_team_id": 15805,
      "away_team_id": 21232,
      "match_url": "https://www.englandrugby.com/fixtures-and-results/match-centre-community?matchId=92520",
      "home_score": 5,
      "away_score": 24
    },
    {
      "date": "2006-03-11",
      "time": "",
      "home_team_id": 10011,
      "away_team_id": 1865,
      "match_url": "https://www.englandrugby.com/fixtures-and-results/match-centre-community?matchId=92523",
      "home_score": 80,
      "away_score": 0
    },
    {
      "date": "2006-03-11",
      "time": "",
      "home_team_id": 11294,
      "away_team_id": 7088,
      "match_url": "https://www.englandrugby.com/fixtures-and-results/match-centre-community?matchId=92524",
      "home_score": 24,
      "away_score": 29
    },
    {
      "date": "2006-03-11",
      "time": "",
      "home_team_id": 15578,
      "away_team_id": 19548,
      "match_url": "https://www.englandrugby.com/fixtures-and-results/match-centre-community?matchId=92526",
      "home_score": 18,
      "away_score": 40
    },
    {
      "date": "2006-03-11",
      "time": "",
      "home_team_id": 16795,
      "away_team_id": 11963,
      "match_url": "https://www.englandrugby.com/fixtures-and-results/match-centre-community?matchId=92528",
      "home_score": 36,
      "away_score": 10
    },
    {
      "date": "2006-03-11",
      "time": "",
      "home_team_id": 19363,
      "away_team_id": 15805,
      "match_url": "https://www.englandrugby.com/fixtures-and-results/match-centre-community?matchId=92527",
      "home_score": 34,
      "away_score": 3
    },
    {
      "date": "2006-03-11",
      "time": "",
      "home_team_id": 21232,
      "away_team_id": 15197,
      "match_url": "https://www.englandrugby.com/fixtures-and-results/match-centre-community?matchId=92525",
      "home_score": 38,
      "away_score": 13
    },
    {
      "date": "2006-03-18",
      "time": "",
      "home_team_id": 19548,
      "away_team_id": 16795,
      "match_url": "https://www.englandrugby.com/fixtures-and-results/match-centre-community?matchId=92521",
      "home_score": 23,
      "away_score": 15
    },
    {
      "date": "2006-03-25",
      "time": "",
      "home_team_id": 1865,
      "away_team_id": 7088,
      "match_url": "https://www.englandrugby.com/fixtures-and-results/match-centre-community?matchId=92529",
      "home_score": 12,
      "away_score": 24
    },
    {
      "date": "2006-03-25",
      "time": "",
      "home_team_id": 11963,
      "away_team_id": 15578,
      "match_url": "https://www.englandrugby.com/fixtures-and-results/match-centre-community?matchId=92533",
      "home_score": 36,
      "away_score": 19
    },
    {
      "date": "2006-03-25",
      "time": "",
      "home_team_id": 15197,
      "away_team_id": 19363,
      "match_url": "https://www.englandrugby.com/fixtures-and-results/match-centre-community?matchId=92532",
      "home_score": 22,
      "away_score": 12
    },
    {
      "date": "2006-03-25",
      "time": "",
      "home_team_id": 15805,
      "away_team_id": 16795,
      "match_url": "https://www.englandrugby.com/fixtures-and-results/match-centre-community?matchId=92534",
      "home_score": 41,
      "away_score": 26
    },
    {
      "date": "2006-03-25",
      "time": "",
      "home_team_id": 19548,
      "away_team_id": 11294,
      "match_url": "https://www.englandrugby.com/fixtures-and-results/match-centre-community?matchId=92531",
      "home_score": 27,
      "away_score": 10
    },
    {
      "date": "2006-04-08",
      "time": "",
      "home_team_id": 1865,
      "away_team_id": 21232,
      "match_url": "https://www.englandrugby.com/fixtures-and-results/match-centre-community?matchId=92535",
      "home_score": 10,
      "away_score": 45
    },
    {
      "date": "2006-04-08",
      "time": "",
      "home_team_id": 7088,
      "away_team_id": 19548,
      "match_url": "https://www.englandrugby.com/fixtures-and-results/match-centre-community?matchId=92536",
      "home_score": 7,
      "away_score": 33
    },
    {
      "date": "2006-04-08",
      "time": "",
      "home_team_id": 11294,
      "away_team_id": 11963,
      "match_url": "https://www.englandrugby.com/fixtures-and-results/match-centre-community?matchId=92538",
      "home_score": 8,
      "away_score": 29
    },
    {
      "date": "2006-04-08",
      "time": "",
      "home_team_id": 15578,
      "away_team_id": 15805,
      "match_url": "https://www.englandrugby.com/fixtures-and-results/match-centre-community?matchId=92540",
      "home_score": 17,
      "away_score": 11
    },
    {
      "date": "2006-04-08",
      "time": "",
      "home_team_id": 16795,
      "away_team_id": 15197,
      "match_url": "https://www.englandrugby.com/fixtures-and-results/match-centre-community?matchId=92539",
      "home_score": 29,
      "away_score": 33
    },
    {
      "date": "2006-04-08",
      "time": "",
      "home_team_id": 19363,
      "away_team_id": 10011,
      "match_url": "https://www.englandrugby.com/fixtures-and-results/match-centre-community?matchId=92537",
      "home_score": 0,
      "away_score": 33
    },
    {
      "date": "2006-04-12",
      "time": "",
      "home_team_id": 10011,
      "away_team_id": 21232,
      "match_url": "https://www.englandrugby.com/fixtures-and-results/match-centre-community?matchId=92530",
      "home_score": 10,
      "away_score": 18
    },
    {
      "date": "2006-04-22",
      "time": "",
      "home_team_id": 10011,
      "away_team_id": 16795,
      "match_url": "https://www.englandrugby.com/fixtures-and-results/match-centre-community?matchId=92544",
      "home_score": 37,
      "away_score": 13
    },
    {
      "date": "2006-04-22",
      "time": "",
      "home_team_id": 11963,
      "away_team_id": 7088,
      "match_url": "https://www.englandrugby.com/fixtures-and-results/match-centre-community?matchId=92543",
      "home_score": 29,
      "away_score": 24
    },
    {
      "date": "2006-04-22",
      "time": "",
      "home_team_id": 15197,
      "away_team_id": 15578,
      "match_url": "https://www.englandrugby.com/fixtures-and-results/match-centre-community?matchId=92546",
      "home_score": 28,
      "away_score": 7
    },
    {
      "date": "2006-04-22",
      "time": "",
      "home_team_id": 15805,
      "away_team_id": 11294,
      "match_url": "https://www.englandrugby.com/fixtures-and-results/match-centre-community?matchId=92545",
      "home_score": 12,
      "away_score": 6
    },
    {
      "date": "2006-04-22",
      "time": "",
      "home_team_id": 19548,
      "away_team_id": 1865,
      "match_url": "https://www.englandrugby.com/fixtures-and-results/match-centre-community?matchId=92541",
      "home_score": 87,
      "away_score": 13
    },
    {
      "date": "2006-04-22",
      "time": "",
      "home_team_id": 21232,
      "away_team_id": 19363,
      "match_url": "https://www.englandrugby.com/fixtures-and-results/match-centre-community?matchId=92542",
      "home_score": 24,
      "away_score": 26
    }
  ]
}
